{
  "title": "sen-form-field",
  "path": "/docs/api/form-field",
  "codePenLinks": [],
  "menu": null,
  "body": [
    "div",
    null
  ],
  "usage": {},
  "props": [
    {
      "name": "label",
      "type": "string",
      "mutable": false,
      "attr": "label",
      "reflectToAttr": false,
      "docs": "<p>Label of the form field</p>\n",
      "docsTags": [],
      "default": "\"\"",
      "values": [
        {
          "type": "string"
        }
      ],
      "optional": false,
      "required": false
    }
  ],
  "methods": [],
  "template": "api",
  "filePath": "./src/components/form-field/form-field.tsx",
  "encapsulation": "shadow",
  "tag": "sen-form-field",
  "docs": "",
  "docsTags": [],
  "events": [],
  "listeners": [],
  "styles": [],
  "slots": [],
  "parts": [],
  "dependents": [],
  "dependencies": [
    "sen-row",
    "sen-col"
  ],
  "dependencyGraph": {
    "sen-form-field": [
      "sen-row",
      "sen-col"
    ]
  },
  "headings": [],
  "pageClass": "page--docs-api-form-field"
}
